mosaic/__init__.py
pymosaic_fits-0.4.2.dist-info/COPYING
pymosaic_fits-0.4.2.dist-info/METADATA
pymosaic_fits-0.4.2.dist-info/WHEEL
pymosaic_fits-0.4.2.dist-info/entry_points.txt
pymosaic_fits-0.4.2.dist-info/top_level.txt
pymosaic_fits-0.4.2.dist-info/RECORD
